setup.py
./__init__.py
./__tryton__.py
./electronic_mail.py
./template.py
./trigger.py
./tests/test_template.py
trytond_electronic_mail_template.egg-info/PKG-INFO
trytond_electronic_mail_template.egg-info/SOURCES.txt
trytond_electronic_mail_template.egg-info/dependency_links.txt
trytond_electronic_mail_template.egg-info/entry_points.txt
trytond_electronic_mail_template.egg-info/not-zip-safe
trytond_electronic_mail_template.egg-info/requires.txt
trytond_electronic_mail_template.egg-info/top_level.txt