Metadata-Version: 1.0
Name: trytond-electronic-mail-template
Version: 2.4.0.1
Summary: Electronic mail template
Home-page: http://openlabs.co.in
Author: Openlabs Technologies & Consulting (P) LTD
Author-email: info@openlabs.co.in
License: GPL-3
Download-URL: http://downloads.tryton.org/2.4.0/
Platform: UNKNOWN
Classifier: Development Status :: 5 - Production/Stable
Classifier: Environment :: Plugins
Classifier: Framework :: Tryton
Classifier: Intended Audience :: Developers
Classifier: Intended Audience :: Financial and Insurance Industry
Classifier: Intended Audience :: Legal Industry
Classifier: Intended Audience :: Manufacturing
Classifier: License :: OSI Approved :: GNU General Public License (GPL)
Classifier: Natural Language :: English
Classifier: Operating System :: OS Independent
Classifier: Programming Language :: Python
Classifier: Topic :: Office/Business
